source_linnworks/__init__.py
source_linnworks/run.py
source_linnworks/schemas/processed_order_details.json
source_linnworks/schemas/processed_orders.json
source_linnworks/schemas/stock_items.json
source_linnworks/schemas/stock_location_details.json
source_linnworks/schemas/stock_locations.json
source_linnworks/source.py
source_linnworks/spec.json
source_linnworks/streams.py
airbyte_source_linnworks-0.1.66.dist-info/METADATA
airbyte_source_linnworks-0.1.66.dist-info/WHEEL
airbyte_source_linnworks-0.1.66.dist-info/entry_points.txt
airbyte_source_linnworks-0.1.66.dist-info/RECORD
